[
    {
        "idLeilao":1,
        "dataInicio": "2024-01-10T08:30:00Z",
        "dataFim": "2024-01-10T20:30:00Z",
        "leilao_estado": "EmLeilao",
        "preco_base": 250.00,
        "custo_envio":10.00,
        "nome_artista":"Leonardo Da Vinki",
        "prod_comprimento":15.00,
        "prod_altura":10.00,
        "prod_largura":8.00,
        "prod_tipo":"Pintura",
        "prod_estado":"Excelente",
        "prod_tecnica":"Pintou,morreu,famosou",
        "prod_descricao":"Descricao descritiva",
        "prod_nome":"Maconha Lisa",
        "prod_peso":200,
        "image":"https://upload.wikimedia.org/wikipedia/commons/e/ec/Mona_Lisa%2C_by_Leonardo_da_Vinci%2C_from_C2RMF_retouched.jpg",
        "idAdmin":2
    },
    {
        "idLeilao":2,
        "dataInicio": "2024-01-10T08:30:00Z",
        "dataFim": "2024-01-10T18:30:00Z",
        "leilao_estado": "EmLeilao",
        "preco_base": 100.00,
        "custo_envio":10.00,
        "nome_artista":"Eduardo Muncha muito",
        "prod_comprimento":15.00,
        "prod_altura":10.00,
        "prod_largura":8.00,
        "prod_tipo":"Pintura",
        "prod_estado":"Excelente",
        "prod_tecnica":"Gritou,Pintou",
        "prod_descricao":"Descricao descritiva",
        "prod_nome":"O grito louco",
        "prod_peso":140,
        "image":"https://upload.wikimedia.org/wikipedia/commons/f/f7/The_Scream_Pastel.jpg",
        "idAdmin":2
    }
]